{
  "type": "lucky:group",
  "luck": 1,
  "outcomes": [
    {
      "type": "lucky:item",
      "item": "minecraft:prismarine",
      "count": {
        "type": "minecraft:uniform",
        "min_inclusive": 4,
        "max_inclusive": 8
      }
    },
    {
      "type": "lucky:item",
      "item": "minecraft:prismarine_bricks",
      "count": {
        "type": "minecraft:uniform",
        "min_inclusive": 4,
        "max_inclusive": 8
      }
    },
    {
      "type": "lucky:item",
      "item": "minecraft:dark_prismarine",
      "count": {
        "type": "minecraft:uniform",
        "min_inclusive": 4,
        "max_inclusive": 8
      }
    },
    {
      "type": "lucky:item",
      "item": "minecraft:prismarine_shard",
      "count": {
        "type": "minecraft:uniform",
        "min_inclusive": 15,
        "max_inclusive": 30
      }
    },
    {
      "type": "lucky:item",
      "item": "minecraft:prismarine_crystals",
      "count": {
        "type": "minecraft:uniform",
        "min_inclusive": 10,
        "max_inclusive": 20
      }
    },
    {
      "type": "lucky:item",
      "item": "minecraft:dark_prismarine",
      "count": {
        "type": "minecraft:uniform",
        "min_inclusive": 4,
        "max_inclusive": 8
      }
    },
    {
      "type": "lucky:particle",
      "particle_type": {
        "type": "minecraft:item",
        "item": {
          "id": "minecraft:splash_potion",
          "components": {
            "potion_contents": {
              "potion": "minecraft:invisibility"
            }
          }
        }
      },
      "count": 100
    },
    {
      "type": "lucky:particle",
      "particle_type": {
        "type": "minecraft:effect"
      },
      "count": 100
    }
  ]
}